fastapify/__init__.py
fastapify/__main__.py
fastapify/application.py
fastapify/main.py
fastapify/module_functionality/__init__.py
fastapify/module_functionality/commands.py
fastapify/module_functionality/templates/__init__.py
fastapify/module_functionality/templates/api.py
fastapify/module_functionality/templates/config.py
fastapify/module_functionality/templates/database.py
fastapify/module_functionality/templates/main.py
fastapify/module_functionality/templates/other_files.py
fastapify-0.0.18.dist-info/licenses/LICENSE
fastapify-0.0.18.dist-info/METADATA
fastapify-0.0.18.dist-info/WHEEL
fastapify-0.0.18.dist-info/entry_points.txt
fastapify-0.0.18.dist-info/top_level.txt
fastapify-0.0.18.dist-info/RECORD
