Metadata-Version: 2.4
Name: fastapify
Version: 0.0.18
Summary: A simple FastAPI factory for creating FastAPI applications.
Home-page: https://github.com/rustamovjavohir/FastApiBuilder
Author: Rustamov Javohir
Author-email: rustamovj366@gmail.com
License: <the license you chose>
Classifier: Programming Language :: Python :: 3.8
Classifier: Operating System :: OS Independent
Requires-Python: >=3.9.0
License-File: LICENSE
Requires-Dist: click==8.1.8
Requires-Dist: fastapi[all]==0.115.8
Requires-Dist: uvicorn[standard]==0.34.0
Requires-Dist: alembic==1.14.1
Requires-Dist: sqlalchemy[asyncio]==2.0.38
Requires-Dist: passlib==1.7.4
Dynamic: author
Dynamic: author-email
Dynamic: classifier
Dynamic: description
Dynamic: description-content-type
Dynamic: home-page
Dynamic: license
Dynamic: license-file
Dynamic: requires-dist
Dynamic: requires-python
Dynamic: summary
